ethos/__init__.py
ethos/_client.py
ethos/_config.py
ethos/_http.py
ethos/exceptions.py
ethos/py.typed
ethos/resources/__init__.py
ethos/resources/activities.py
ethos/resources/base.py
ethos/resources/contributions.py
ethos/resources/endorsements.py
ethos/resources/invitations.py
ethos/resources/markets.py
ethos/resources/notifications.py
ethos/resources/profiles.py
ethos/resources/replies.py
ethos/resources/reviews.py
ethos/resources/scores.py
ethos/resources/users.py
ethos/resources/votes.py
ethos/resources/vouches.py
ethos/resources/xp.py
ethos/types/__init__.py
ethos/types/activity.py
ethos/types/contribution.py
ethos/types/endorsement.py
ethos/types/invitation.py
ethos/types/market.py
ethos/types/notification.py
ethos/types/pagination.py
ethos/types/profile.py
ethos/types/reply.py
ethos/types/review.py
ethos/types/score.py
ethos/types/user.py
ethos/types/vote.py
ethos/types/vouch.py
ethos/types/xp.py
ethos_py-0.2.3.dist-info/METADATA
ethos_py-0.2.3.dist-info/WHEEL
ethos_py-0.2.3.dist-info/licenses/LICENSE
ethos_py-0.2.3.dist-info/RECORD
